xnb/__init__.py
xnb/_bandwidth_functions.py
xnb/_kde_object.py
xnb/_progress_bar.py
xnb/enums.py
xnb/explicable_naive_bayes.py
xnb-0.4.5.dist-info/METADATA
xnb-0.4.5.dist-info/WHEEL
xnb-0.4.5.dist-info/licenses/LICENSE
xnb-0.4.5.dist-info/RECORD
