Metadata-Version: 2.4
Name: xnb
Version: 0.4.5
Summary: Explainable Naive Bayes (XNB) classifier. Using KDE for feature selection and Naive Bayes for prediction.
License-Expression: MIT
License-File: LICENSE
Keywords: KDE,naive bayes,classification,feature selection,machine learning,explicability,kernel density,class-specific
Author: Cayetano Romero Vargas
Author-email: cromerovargas2d@gmail.com
Requires-Python: >=3.9.0
Classifier: Development Status :: 5 - Production/Stable
Classifier: Intended Audience :: Science/Research
Classifier: License :: OSI Approved :: MIT License
Classifier: Programming Language :: Python :: 3.9
Classifier: Programming Language :: Python :: 3.10
Classifier: Programming Language :: Python :: 3.11
Classifier: Topic :: Software Development :: Libraries :: Python Modules
Classifier: Topic :: Scientific/Engineering :: Artificial Intelligence
Requires-Dist: alive-progress (>=3.1.5,<4.0.0)
Requires-Dist: numpy (>=2.0.1,<3.0.0)
Requires-Dist: pandas (>=2.2.2,<3.0.0)
Requires-Dist: scikit-learn (>=1.5.1,<2.0.0)
Project-URL: Changelog, https://github.com/sorul/xnb/blob/master/CHANGELOG.md
Project-URL: Repository, https://github.com/sorul/xnb
